{
  "task_id": "tidymodels_parsnip_1317",
  "source": {
    "repo": "tidymodels/parsnip",
    "pr_number": 1317,
    "base_commit": "77e08226814f7f51849450671ca1600b00e630aa",
    "head_commit": "11dbcce817d7b81bf38c5a89af32220fd5559675",
    "merged_commit": "bf4e28262a5f6c3e80aa28b4d16de2393be5ef36",
    "pr_url": "https://github.com/tidymodels/parsnip/pull/1317",
    "merged_at": "2026-01-06T16:04:21+00:00",
    "issue_url": "https://github.com/tidymodels/parsnip/issues/1316"
  },
  "problem_statement": {
    "title": "stop out of bounds `iterationrange` for xgboost",
    "body": "To close #1316 \r\n\r\nEDIT: Adding a bit more context. This was technically an issue before too, where asking out of bounds also gave different results. However, it now causes an error, hence why we have to fix it\r\n\r\n``` r\r\nlibrary(parsnip)\r\nlibrary(tune)\r\nlibrary(workflows)\r\nlibrary(recipes)\r\nlibrary(rsample)\r\nlibrary(yardstick)\r\n\r\n# Create simple data\r\nset.seed(42)\r\ndata <- data.frame(\r\n  x1 = rnorm(50),\r\n  x2 = rnorm(50),\r\n  y = rnorm(50)\r\n)\r\n\r\n# Create recipe\r\nrec <- recipe(y ~ ., data = data)\r\n\r\n# Problematic model specification\r\nxgb_spec <- boost_tree(\r\n  trees = tune(),  # This parameter causes the issue\r\n  engine = \"xgboost\", \r\n  mode = \"regression\"\r\n)\r\n\r\n# Create workflow\r\nwf <- workflow() %>%\r\n  add_recipe(rec) %>%\r\n  add_model(xgb_spec)\r\n\r\n# Create CV folds\r\ncv_folds <- vfold_cv(data, v = 2)\r\n\r\n# Simple grid\r\ngrid <- data.frame(trees = c(5, 10))\r\n\r\n# This produces the error:\r\ntune_grid(\r\n  wf,\r\n  resamples = cv_folds,\r\n  grid = grid,\r\n  metrics = metric_set(rmse)\r\n)\r\n#> # Tuning results\r\n#> # 2-fold cross-validation \r\n#> # A tibble: 2 \u00d7 4\r\n#>   splits          id    .metrics         .notes          \r\n#>   <list>          <chr> <list>           <list>          \r\n#> 1 <split [25/25]> Fold1 <tibble [2 \u00d7 5]> <tibble [0 \u00d7 4]>\r\n#> 2 <split [25/25]> Fold2 <tibble [2 \u00d7 5]> <tibble [0 \u00d7 4]>\r\n```",
    "issue_title": "boost_tree() with new xgboost and trees = tune() fails with \"Out of range for tree layers\"",
    "issue_body": "## The problem\n\nWhen using `parsnip::boost_tree()` with `trees = tune()` and the new XGBoost package, hyperparameter tuning with `tune::tune_grid()` consistently fails with errors of the type\n\n```\n\u2192 A | error:   \u2139 In index: 1.\n               Caused by error in `predict.xgb.Booster()`:\n               ! [10:23:27] src/gbm/gbtree.h:124: Check failed: end <= model.BoostedRounds() (11 vs. 10) : Out of range for tree layers.\n```\n\nThis appears to be an indexing issue where parsnip is requesting more trees than the model actually contains during the prediction phase of cross-validation.\n\n## Reproducible example\n\n```\nlibrary(parsnip)\nlibrary(tune)\nlibrary(workflows)\nlibrary(recipes)\nlibrary(rsample)\nlibrary(yardstick)\n\n# Create simple data\nset.seed(42)\ndata <- data.frame(\n  x1 = rnorm(50),\n  x2 = rnorm(50),\n  y = rnorm(50)\n)\n\n# Create recipe\nrec <- recipe(y ~ ., data = data)\n\n# Problematic model specification\nxgb_spec <- boost_tree(\n  trees = tune(),  # This parameter causes the issue\n  engine = \"xgboost\", \n  mode = \"regression\"\n)\n\n# Create workflow\nwf <- workflow() %>%\n  add_recipe(rec) %>%\n  add_model(xgb_spec)\n\n# Create CV folds\ncv_folds <- vfold_cv(data, v = 2)\n\n# Simple grid\ngrid <- data.frame(trees = c(5, 10))\n\n# This produces the error:\nresult <- tune_grid(\n  wf,\n  resamples = cv_folds,\n  grid = grid,\n  metrics = metric_set(rmse)\n)\n```\nThis gives the output:\n\n```\n[1] \"XGBoost version:3.1.2.1\"\nAttempting to tune XGBoost with trees parameter...\nThis should produce the 'Out of range for tree layers' error\n\ni Fold1: preprocessor 1/1\ni Fold1: preprocessor 1/1, model 1/1\ni Fold1: preprocessor 1/1, model 1/1 (predictions)\ni Fold1: preprocessor 1/1, model 1/1 (predictions)\n\u2192 A | error:   \u2139 In index: 1.\n               Caused by error in `predict.xgb.Booster()`:\n               ! [10:23:27] src/gbm/gbtree.h:124: Check failed: end <= model.BoostedRounds() (11 vs. 10) : Out of range for tree layers.\n               Stack trace:\n                 [bt] (0) /home/jullum/R/x86_64-pc-linux-gnu-library/4.3/xgboost/libs/xgboost.so(+0x7d55f) [0x7fa05c0c355f]\n                 [bt] (1) /home/jullum/R/x86_64-pc-linux-gnu-library/4.3/xgboost/libs/xgboost.so(+0x1ed10c) [0x7fa05c23310c]\n                 [bt] (2) /home/jullum/R/x86_64-pc-linux-gnu-library/4.3/xgboost/libs/xgboost.so(+0x1df2b2) [0x7fa05c2252b2]\n                 [bt] (3) /home/jullum/R/x86_64-pc-linux-gnu-library/4.3/xgboost/libs/xgboost.so(+0x460bec) [0x7fa05c4a6bec]\n                 [bt] (4) /home/jullum/R/x86_64-pc-linux-gnu-library/4.3/xgboost/libs/xgboost.so(XGBoosterPredictFromDMatrix+0x3bc) [0x7fa05c5a850c]\n                 [bt] (5) /home/jullum/R/x86_64-pc-linux-gnu-library/4.3/xgboost/libs/xgboost.so(+0x7a7d1) [0x7fa05c0c07d1]\n                 [bt] (6) /usr/lib/R/lib/libR.so(+0x10269e) [0x7fa0659f669e]\n                 [bt] (7) /usr/lib/R/lib/libR.so(+0x14740c) [0x7fa065a3b40c]\n                 [bt] (8) /usr/lib/R/lib/libR.so(Rf_eval+0x180) [0x7fa065a4\ni Fold2: preprocessor 1/1\ni Fold2: preprocessor 1/1, model 1/1\ni Fold2: preprocessor 1/1, model 1/1 (predictions)\ni Fold2: preprocessor 1/1, model 1/1 (predictions)\n\nTuning results:\n# A tibble: 1 \u00d7 7\n  trees .metric .estimator  mean     n std_err .config        \n  <dbl> <chr>   <chr>      <dbl> <int>   <dbl> <chr>          \n1     5 rmse    standard    1.24     2  0.0736 pre0_mod1_post0\n```\n\nI.e. the model with 10 trees fails and is not included in the comparison. \nUsing a longer set of trees, it always gives an error for the highest number. \n\nI have verified that the above runs fine with the old xgboost version (1.7.7.1), so I believe this is caused a bug in how the number of trees are extracted from the new xgboost version. There might be an issue with the iterationrange here? https://github.com/tidymodels/parsnip/blob/77e08226814f7f51849450671ca1600b00e630aa/R/boost_tree.R#L653-L668\n\nHere is my sessionInfo:\n\n```\nR version 4.3.3 (2024-02-29)\nPlatform: x86_64-pc-linux-gnu (64-bit)\nRunning under: Ubuntu 24.04.3 LTS\n\nMatrix products: default\nBLAS:   /usr/lib/x86_64-linux-gnu/blas/libblas.so.3.12.0 \nLAPACK: /usr/lib/x86_64-linux-gnu/lapack/liblapack.so.3.12.0\n\nlocale:\n [1] LC_CTYPE=C.UTF-8       LC_NUMERIC=C           LC_TIME=C.UTF-8       \n [4] LC_COLLATE=C.UTF-8     LC_MONETARY=C.UTF-8    LC_MESSAGES=C.UTF-8   \n [7] LC_PAPER=C.UTF-8       LC_NAME=C              LC_ADDRESS=C          \n[10] LC_TELEPHONE=C         LC_MEASUREMENT=C.UTF-8 LC_IDENTIFICATION=C   \n\ntime zone: Europe/Oslo\ntzcode source: system (glibc)\n\nattached base packages:\n[1] stats     graphics  grDevices utils     datasets  methods   base     \n\nother attached packages:\n[1] xgboost_3.1.2.1 hardhat_1.4.2   yardstick_1.3.2 rsample_1.3.1  \n[5] recipes_1.3.1   dplyr_1.1.4     workflows_1.3.0 tune_2.0.1     \n[9] parsnip_1.4.0  \n\nloaded via a namespace (and not attached):\n [1] utf8_1.2.6          future_1.68.0       generics_0.1.4     \n [4] tidyr_1.3.1         class_7.3-22        lattice_0.22-5     \n [7] lhs_1.2.0           DiceDesign_1.10     listenv_0.10.0     \n[10] digest_0.6.39       magrittr_2.0.4      timechange_0.3.0   \n[13] grid_4.3.3          RColorBrewer_1.1-3  jsonlite_2.0.0     \n[16] Matrix_1.6-5        nnet_7.3-19         brio_1.1.5         \n[19] survival_3.5-8      GPfit_1.0-9         purrr_1.2.0        \n[22] scales_1.4.0        codetools_0.2-19    lava_1.8.2         \n[25] cli_3.6.5           rlang_1.1.6         parallelly_1.46.0  \n[28] future.apply_1.20.1 splines_4.3.3       withr_3.0.2        \n[31] dials_1.4.2         prodlim_2025.04.28  tailor_0.1.0       \n[34] tools_4.3.3         parallel_4.3.3      ggplot2_4.0.1      \n[37] globals_0.18.0      vctrs_0.6.5         R6_2.6.1           \n[40] rpart_4.1.23        lubridate_1.9.4     lifecycle_1.0.4    \n[43] MASS_7.3-60.0.1     furrr_0.3.1         pkgconfig_2.0.3    \n[46] sparsevctrs_0.3.4   pillar_1.11.1       gtable_0.3.6       \n[49] glue_1.8.0          data.table_1.17.8   Rcpp_1.1.0         \n[52] tibble_3.3.0        tidyselect_1.2.1    farver_2.1.2       \n[55] ipred_0.9-15        testthat_3.3.1      timeDate_4051.111  \n[58] gower_1.0.2         compiler_4.3.3      S7_0.2.1           \n```\n\nI hope this issue can be resolved. Please let me know if I can be of any assistance\n\n< -- ~~~~~~~~~~~~~~~~~~~~~~~~~~~~~~~~~~~~~~~~~~~~~~~~~~~~~~~~~~~~ -->\n\n"
  },
  "patch": "diff --git a/.github/workflows/R-CMD-check.yaml b/.github/workflows/R-CMD-check.yaml\nindex 135e8834f..94a0bedc1 100644\n--- a/.github/workflows/R-CMD-check.yaml\n+++ b/.github/workflows/R-CMD-check.yaml\n@@ -56,7 +56,7 @@ jobs:\n \n       - uses: r-lib/actions/setup-r-dependencies@v2\n         with:\n-          extra-packages: any::rcmdcheck\n+          extra-packages: any::rcmdcheck, xgboost=?ignore-before-r=4.3.0\n           needs: check\n \n       - name: Install dev reticulate\ndiff --git a/NEWS.md b/NEWS.md\nindex 0282b2f30..7966795a2 100644\n--- a/NEWS.md\n+++ b/NEWS.md\n@@ -1,5 +1,7 @@\n # parsnip (development version)\n \n+* Fixed bug where xgboost mdoels would fail to predict when `trees` matched number of trees in model. (#1316)\n+\n # parsnip 1.4.0\n \n * Fixes issue with running predictions for Decision Trees in Spark (#1309)\ndiff --git a/R/boost_tree.R b/R/boost_tree.R\nindex beb11b46f..b15c6f6af 100644\n--- a/R/boost_tree.R\n+++ b/R/boost_tree.R\n@@ -653,16 +653,19 @@ multi_predict._xgb.Booster <-\n xgb_by_tree <- function(tree, object, new_data, type, ...) {\n   rlang::check_installed(\"xgboost\")\n   if (utils::packageVersion(\"xgboost\") >= \"2.0.0.0\") {\n+    # avoid out of range\n+    range_end <- min(nrow(attr(object$fit, \"evaluation_log\")), tree + 1)\n+\n     pred <- xgb_predict(\n       object$fit,\n       new_data = new_data,\n-      iterationrange = c(1, tree + 1)\n+      iterationrange = c(1, range_end)\n     )\n   } else {\n     pred <- xgb_predict(\n       object$fit,\n       new_data = new_data,\n-      iterationrange = c(1, tree + 1),\n+      iterationrange = c(1, min(object$fit$niter, tree + 1)),\n       ntreelimit = NULL\n     )\n   }",
  "test_patch": "diff --git a/tests/testthat/test-boost_tree_xgboost.R b/tests/testthat/test-boost_tree_xgboost.R\nindex cdc60849c..064322dd8 100644\n--- a/tests/testthat/test-boost_tree_xgboost.R\n+++ b/tests/testthat/test-boost_tree_xgboost.R\n@@ -337,6 +337,30 @@ test_that('submodel prediction', {\n   )\n })\n \n+test_that(\"submodel prediction doesn't error if trees match number of trees (#1316)\", {\n+  skip_if_not_installed(\"xgboost\")\n+  skip_on_cran()\n+\n+  ctrl$verbosity <- 0L\n+\n+  reg_fit <-\n+    boost_tree(trees = 20, mode = \"regression\") |>\n+    set_engine(\"xgboost\") |>\n+    fit(mpg ~ ., data = mtcars[-(1:4), ])\n+\n+  x <- xgboost::xgb.DMatrix(as.matrix(mtcars[1:4, -1]))\n+\n+  pruned_pred <- predict(\n+    extract_fit_engine(reg_fit),\n+    x,\n+    iterationrange = c(1, 20)\n+  )\n+\n+  mp_res <- multi_predict(reg_fit, new_data = mtcars[1:4, -1], trees = 20)\n+  mp_res <- do.call(\"rbind\", mp_res$.pred)\n+  expect_equal(mp_res[[\".pred\"]], pruned_pred)\n+})\n+\n # ------------------------------------------------------------------------------\n \n test_that('validation sets', {\n",
  "tests": {
    "fail_to_pass": [
      "test_that(\"submodel prediction doesn't error if trees match number of trees (#1316)\", { ... }) - verifies that multi_predict with trees=20 works on a model trained with 20 trees"
    ],
    "pass_to_pass": [
      "Existing submodel prediction tests should continue to pass",
      "Tests for predictions with trees < model's tree count should work"
    ]
  },
  "metadata": {
    "task_type": "bug_fix",
    "difficulty": "medium",
    "quality_score": 8,
    "mined_at": "2026-02-22T18:58:36.275427+00:00",
    "key_changes": [
      "Add bounds checking using min() to prevent iterationrange from exceeding model's actual tree count",
      "Handle both xgboost >= 2.0.0.0 (use evaluation_log) and older versions (use niter)",
      "The iterationrange upper bound should be min(actual_iterations, tree + 1)"
    ],
    "potential_pitfalls": [
      "Off-by-one errors: iterationrange is 1-indexed with exclusive upper bound (c(1, n+1) gives n iterations)",
      "Not handling both xgboost version cases (>= 2.0.0.0 and older)",
      "Using wrong attribute to determine number of iterations",
      "Forgetting that trees parameter from user is 0-indexed conceptually but iterationrange needs adjustment"
    ]
  },
  "instruction": "Fix the bug in the `xgb_by_tree()` function where requesting predictions with `trees` parameter equal to the number of trees in the model causes an 'Out of range for tree layers' error in xgboost. The function should properly bound the `iterationrange` parameter to avoid requesting more iterations than the model contains. This affects the `multi_predict` functionality when users request predictions for a specific number of trees that matches or exceeds what was trained.",
  "context": "The `xgb_by_tree()` function in R/boost_tree.R handles per-tree predictions for xgboost models. The function uses `iterationrange` parameter which is 1-indexed with exclusive upper bound. The bug occurs when `tree + 1` exceeds the actual number of trees in the model. For xgboost >= 2.0.0.0, the number of iterations can be obtained via `nrow(attr(object$fit, \"evaluation_log\"))`. For older versions, use `object$fit$niter`. The fix requires using `min()` to bound the range_end appropriately."
}